cryptide/__init__.py
cryptide/IC/__init__.py
cryptide/IC/functions.py
cryptide/IC/reference_data.py
cryptide/ascii/__init__.py
cryptide/ascii/functions.py
cryptide/bytes/__init__.py
cryptide/bytes/functions.py
cryptide/enigma_bf/__init__.py
cryptide/enigma_bf/functions.py
cryptide-0.0.4.dist-info/LICENSE
cryptide-0.0.4.dist-info/METADATA
cryptide-0.0.4.dist-info/WHEEL
cryptide-0.0.4.dist-info/top_level.txt
cryptide-0.0.4.dist-info/RECORD
