Metadata-Version: 2.1
Name: cryptide
Version: 0.0.4
Summary: To help you for les brutes force 
Home-page: UNKNOWN
Author: Ursial
Author-email: ursial.alain@gmail.com
License: UNKNOWN
Platform: UNKNOWN
Classifier: Programming Language :: Python :: 3
Classifier: License :: OSI Approved :: MIT License
Classifier: Operating System :: OS Independent
Requires-Python: >=3.6
Requires-Dist: Unidecode
Requires-Dist: py-enigma
